MANIFEST.in
setup.py
cellworld/QuickBundles.py
cellworld/__init__.py
cellworld/agent_markers.py
cellworld/capture.py
cellworld/cell.py
cellworld/coordinates.py
cellworld/display.py
cellworld/experiment.py
cellworld/frame.py
cellworld/graph.py
cellworld/info.py
cellworld/license.txt
cellworld/location.py
cellworld/path.py
cellworld/readme.md
cellworld/setup.cfg
cellworld/shape.py
cellworld/util.py
cellworld/visibility.py
cellworld/world.py
cellworld.egg-info/PKG-INFO
cellworld.egg-info/SOURCES.txt
cellworld.egg-info/dependency_links.txt
cellworld.egg-info/not-zip-safe
cellworld.egg-info/requires.txt
cellworld.egg-info/top_level.txt
cellworld/__pycache__/QuickBundles.cpython-39.pyc
cellworld/__pycache__/__init__.cpython-311.pyc
cellworld/__pycache__/__init__.cpython-39.pyc
cellworld/__pycache__/agent_markers.cpython-39.pyc
cellworld/__pycache__/capture.cpython-39.pyc
cellworld/__pycache__/cell.cpython-39.pyc
cellworld/__pycache__/coordinates.cpython-39.pyc
cellworld/__pycache__/display.cpython-39.pyc
cellworld/__pycache__/experiment.cpython-39.pyc
cellworld/__pycache__/frame.cpython-39.pyc
cellworld/__pycache__/graph.cpython-39.pyc
cellworld/__pycache__/info.cpython-39.pyc
cellworld/__pycache__/location.cpython-39.pyc
cellworld/__pycache__/path.cpython-39.pyc
cellworld/__pycache__/shape.cpython-311.pyc
cellworld/__pycache__/shape.cpython-39.pyc
cellworld/__pycache__/util.cpython-39.pyc
cellworld/__pycache__/visibility.cpython-39.pyc
cellworld/__pycache__/world.cpython-39.pyc