Metadata-Version: 2.1
Name: cellworld
Version: 0.0.390
Summary: Maciver Lab computational biology research package
Author: german espinosa
Author-email: germanespinosa@gmail.com
License: MIT
Requires-Dist: numpy
Requires-Dist: scipy
Requires-Dist: matplotlib
Requires-Dist: json-cpp>=1.0.77
Requires-Dist: tcp-messages
Requires-Dist: networkx
Requires-Dist: cv
